pinferencia/__init__.py
pinferencia/api_manager.py
pinferencia/apis/__init__.py
pinferencia/apis/default/__init__.py
pinferencia/apis/default/index.py
pinferencia/apis/default/v1/__init__.py
pinferencia/apis/default/v1/config.py
pinferencia/apis/default/v1/models.py
pinferencia/apis/default/v1/parsers.py
pinferencia/apis/default/v1/routers/__init__.py
pinferencia/apis/default/v1/routers/basic.py
pinferencia/apis/default/v1/routers/management.py
pinferencia/apis/default/v1/routers/metadata.py
pinferencia/apis/kserve/__init__.py
pinferencia/apis/kserve/v1/__init__.py
pinferencia/apis/kserve/v1/config.py
pinferencia/apis/kserve/v1/models.py
pinferencia/apis/kserve/v1/parsers.py
pinferencia/apis/kserve/v1/routers/__init__.py
pinferencia/apis/kserve/v1/routers/metadata.py
pinferencia/apis/kserve/v1/routers/predict.py
pinferencia/apis/kserve/v2/__init__.py
pinferencia/apis/kserve/v2/config.py
pinferencia/apis/kserve/v2/models.py
pinferencia/apis/kserve/v2/parsers.py
pinferencia/apis/kserve/v2/routers/__init__.py
pinferencia/apis/kserve/v2/routers/metadata.py
pinferencia/apis/kserve/v2/routers/predict.py
pinferencia/app.py
pinferencia/config.py
pinferencia/context.py
pinferencia/decorators.py
pinferencia/frontend/__init__.py
pinferencia/frontend/api_manager/__init__.py
pinferencia/frontend/api_manager/base.py
pinferencia/frontend/api_manager/default.py
pinferencia/frontend/app.py
pinferencia/frontend/config.py
pinferencia/frontend/model_manager.py
pinferencia/frontend/templates/__init__.py
pinferencia/frontend/templates/base.py
pinferencia/frontend/templates/camera_image_to_image.py
pinferencia/frontend/templates/camera_image_to_text.py
pinferencia/frontend/templates/image_classification.py
pinferencia/frontend/templates/image_style_transfer.py
pinferencia/frontend/templates/image_to_image.py
pinferencia/frontend/templates/image_to_text.py
pinferencia/frontend/templates/raw_request.py
pinferencia/frontend/templates/text_to_image.py
pinferencia-0.2.1.dist-info/entry_points.txt
pinferencia-0.2.1.dist-info/LICENSE
pinferencia-0.2.1.dist-info/WHEEL
pinferencia-0.2.1.dist-info/METADATA
pinferencia-0.2.1.dist-info/RECORD
